bip-0039/chinese_simplified.txt
bip-0039/chinese_traditional.txt
bip-0039/english.txt
bip-0039/french.txt
bip-0039/italian.txt
bip-0039/japanese.txt
bip-0039/korean.txt
bip-0039/russian.txt
bip-0039/spanish.txt
mnemoize.py
py.typed
mnemoize-0.1.1.dist-info/LICENSE
mnemoize-0.1.1.dist-info/WHEEL
mnemoize-0.1.1.dist-info/METADATA
mnemoize-0.1.1.dist-info/RECORD
